LICENSE
nv/__init__.py
nv/utils/__init__.py
nv/utils/collections/__init__.py
nv/utils/collections/mappings/__init__.py
nv/utils/collections/mappings/helpers.py
nv/utils/collections/mappings/objectdict.py
nv/utils/collections/sequences/__init__.py
nv/utils/collections/sequences/chainlist.py
nv/utils/collections/sequences/utils.py
nv/utils/collections/sets.py
nv/utils/collections/structures/__init__.py
nv/utils/collections/structures/merge.py
nv/utils/collections/structures/serializer.py
nv/utils/formatters/__init__.py
nv/utils/formatters/datetime.py
nv/utils/formatters/string.py
nv/utils/introspect/__init__.py
nv/utils/introspect/dotted_path.py
nv/utils/introspect/helpers.py
nv/utils/models/__init__.py
nv/utils/models/singleton.py
nv/utils/models/translatables.py
nv/utils/parsers/__init__.py
nv/utils/parsers/parser.py
nv/utils/parsers/string/__init__.py
nv/utils/parsers/string/boolean.py
nv/utils/parsers/string/bytes.py
nv/utils/parsers/string/datetime.py
nv/utils/parsers/string/parser.py
nv/utils/path.py
nv/utils/serializers/__init__.py
nv/utils/serializers/dotenv.py
nv/utils/serializers/msgpack.py
nv/utils/tables/__init__.py
nv/utils/tables/csv.py
nv/utils/tables/utils.py
nv/utils/tables/xls.py
nv/utils/tables/xls_read.py
nv/utils/tables/xls_write.py
nv/utils/tables/xlsx.py
nv_utils-0.2.0.dist-info/LICENSE
nv_utils-0.2.0.dist-info/WHEEL
nv_utils-0.2.0.dist-info/METADATA
nv_utils-0.2.0.dist-info/RECORD
