Metadata-Version: 2.1
Name: nv-utils
Version: 0.2.0
Summary: Parsers, formatters, data structures and helpers for Python 3 (>=3.9)
Home-page: https://github.com/gstos/nv-utils
License: MIT
Author: Gustavo Santos
Author-email: gustavo@next.ventures
Requires-Python: >=3.9,<4.0
Classifier: License :: OSI Approved :: MIT License
Classifier: Operating System :: OS Independent
Classifier: Programming Language :: Python :: 3
Classifier: Programming Language :: Python :: 3.10
Classifier: Programming Language :: Python :: 3.9
Classifier: Topic :: Software Development :: Libraries :: Python Modules
Provides-Extra: all
Provides-Extra: msgpack
Provides-Extra: pytz
Provides-Extra: xls
Provides-Extra: xlsx
Provides-Extra: xml
Requires-Dist: dicttoxml (>=1.7.4,<2.0.0); extra == "xml" or extra == "all"
Requires-Dist: msgpack-python (>=0.5.6,<0.6.0); extra == "msgpack" or extra == "all"
Requires-Dist: openpyxl (>=3.0.5,<4.0.0); extra == "xlsx" or extra == "all"
Requires-Dist: pytz (>=2021.1,<2022.0); extra == "pytz" or extra == "all"
Requires-Dist: xlrd (>=2.0.1,<3.0.0); extra == "xls" or extra == "all"
Requires-Dist: xlwt (>=1.3.0,<2.0.0); extra == "xls" or extra == "all"
Requires-Dist: xmltodict (>=0.12.0,<0.13.0); extra == "xml" or extra == "all"
Project-URL: Repository, https://github.com/gstos/nv-utils
